{
  "character_id": "0179",
  "character_name": "0179_black_24_male",
  "metadata": {
    "img": "XXXXXXX",
    "age": "24",
    "sex": "male",
    "ethnicity": "black",
    "face_prompt": "Kwame Boateng as a 24 year old black man, with short dreadlocks",
    "id": "0179",
    "name": "0179_black_24_male",
    "image": "image180"
  },
  "migration_timestamp": "2025-10-15T07:38:31.449789",
  "base_images": [
    {
      "filename": "0179_black_24_male_base.jpg",
      "s3_url": "https://story-boards-assets.s3.us-west-1.amazonaws.com/system_actors/base_images/0179_black_24_male_base.jpg",
      "status": "synced",
      "format": "jpeg"
    }
  ],
  "scene_images": [],
  "statistics": {
    "total_files": 1,
    "total_size_bytes": 1327426,
    "total_size_mb": 1.27,
    "base_images_count": 1,
    "scene_images_count": 0,
    "training_images_count": 0,
    "training_data_size_bytes": 0,
    "training_data_size_mb": 0.0,
    "training_synced_count": 0,
    "training_local_only_count": 0
  },
  "status": "success",
  "training_data": [],
  "training_data_updated": "2025-10-17T16:46:16.819361",
  "poster_frames": {
    "standard": {
      "webp_sm": "https://story-boards-assets.s3.us-west-1.amazonaws.com/system_actors/poster_frames/0179_black_24_male_poster_sm.webp",
      "webp_md": "https://story-boards-assets.s3.us-west-1.amazonaws.com/system_actors/poster_frames/0179_black_24_male_poster_md.webp",
      "webp_lg": "https://story-boards-assets.s3.us-west-1.amazonaws.com/system_actors/poster_frames/0179_black_24_male_poster_lg.webp",
      "png": "https://story-boards-assets.s3.us-west-1.amazonaws.com/system_actors/poster_frames/0179_black_24_male_poster.png"
    },
    "accelerated": {
      "webp_sm": "https://story-boards-assets.s3-accelerate.amazonaws.com/system_actors/poster_frames/0179_black_24_male_poster_sm.webp",
      "webp_md": "https://story-boards-assets.s3-accelerate.amazonaws.com/system_actors/poster_frames/0179_black_24_male_poster_md.webp",
      "webp_lg": "https://story-boards-assets.s3-accelerate.amazonaws.com/system_actors/poster_frames/0179_black_24_male_poster_lg.webp",
      "png": "https://story-boards-assets.s3-accelerate.amazonaws.com/system_actors/poster_frames/0179_black_24_male_poster.png"
    }
  },
  "lora_model": {
    "filename": "0179_black_24_male.safetensors",
    "s3_url": "https://story-boards-assets.s3.us-west-1.amazonaws.com/system_actors/lora_models/0179_black_24_male.safetensors",
    "s3_accelerated_url": "https://story-boards-assets.s3-accelerate.amazonaws.com/system_actors/lora_models/0179_black_24_male.safetensors",
    "size_bytes": 216876456,
    "size_mb": 206.83,
    "md5_hash": "1061948dab5346f7a1f92448d4c09de1-26",
    "last_modified": "2025-05-16T07:04:11+00:00",
    "created_date": "2025-05-16",
    "format": "safetensors"
  },
  "lora_model_updated": "2025-10-17T21:51:49.003740"
}